Workbook

Sheet 設定
A1: 輸入型 仕入れ判定ツール — 設定
A2: 黄色セル（青字）を自分の条件に合わせて書き換えてください。他シートはすべてここを参照します。
A4: 項目 | B4: 値 | C4: 根拠・メモ
A5: 為替レート（円/USD） | B5: 150 | C5: 仮の値。仕入れ当日のレートに必ず更新する（カード会社の換算レートが最も正確）
A6: カード決済・為替手数料率 | B6: 0.025 | C6: 海外決済時のカード会社手数料。カード会社により約1.6〜3%。規約で確認
A7: 関税率 | B7: 0 | C7: トレーディングカードは無税とされることが多いが、品目分類は税関の判断。事前教示制度・税関相談で確認
A8: 輸入消費税率 | B8: 0.1 | C8: 国税7.8%＋地方税2.2%
A9: 少額免税ライン（課税価格・円） | B9: 10000 | C9: 1回の輸入の課税価格合計が1万円以下なら関税・消費税が免除（関税定率法14条18号）。最新情報は税関サイトで確認
A10: 通関手数料（1件あたり・円） | B10: 200 | C10: 日本郵便の例。クーリエ（FedEx/DHL等）は別途かかる場合あり
A11: 国内販売手数料率 | B11: 0.1 | C11: メルカリ10%。販路を変える場合は書き換え
A12: 国内送料（1件あたり・円） | B12: 230 | C12: 例: 匿名配送の小型便＋スリーブ・ローダー・梱包材。PSA鑑定品は厚みで送料が上がる
A13: 最低利益額（1件・円） | B13: 3000 | C13: これを下回る案件は見送り
A14: 最低利益率 | B14: 0.15 | C14: これを下回る案件は見送り（相場の下振れ・値下げ交渉の余裕）
A15: 月の目標利益（円） | B15: 100000 | C15: ユーザー目標: 最低月10万円
A18: ※税・手数料・法規制は変わります。数値はあくまで初期値で、実行前に公式情報で確認してください。

Sheet 仕入れ判定
A1: カード名 | B1: 型番/状態 | C1: 仕入先 | D1: 商品価格(USD) | E1: 海外送料(USD) | F1: 転送料・その他(円) | G1: 想定販売価格(円) | H1: 販売価格の根拠 | I1: 仕入原価(円) | J1: 課税価格(円) | K1: 関税(円) | L1: 輸入消費税(円) | M1: 通関手数料(円) | N1: 総仕入コスト(円) | O1: 販売手数料(円) | P1: 国内送料(円) | Q1: 利益(円) | R1: 利益率 | S1: 判定
A2: （記入例）リザードン | B2: PSA10 | C2: eBay | D2: 180 | E2: 25 | F2: 1500 | G2: 45000 | H2: メルカリSold直近5件平均 | I2: =IF(D2="","",(D2+E2)*設定!$B$5*(1+設定!$B$6)+F2) -> 33018.75 | J2: =IF(D2="","",ROUND((D2+E2)*設定!$B$5,0)) -> 30750 | K2: =IF(D2="","",IF(J2<=設定!$B$9,0,ROUNDDOWN(J2*設定!$B$7,0))) -> 0 | L2: =IF(D2="","",IF(J2<=設定!$B$9,0,ROUNDDOWN((J2+K2)*設定!$B$8,0))) -> 3075 | M2: =IF(D2="","",IF(J2<=設定!$B$9,0,設定!$B$10)) -> 200 | N2: =IF(D2="","",I2+K2+L2+M2) -> 36293.75 | O2: =IF(G2="","",ROUNDDOWN(G2*設定!$B$11,0)) -> 4500 | P2: =IF(G2="","",設定!$B$12) -> 230 | Q2: =IF(OR(D2="",G2=""),"",G2-O2-P2-N2) -> 3976.25 | R2: =IF(OR(Q2="",G2=0),"",Q2/G2) -> 0.088361111 | S2: =IF(Q2="","",IF(AND(Q2>=設定!$B$13,R2>=設定!$B$14),"仕入れOK","見送り")) -> 見送り
I3: =IF(D3="","",(D3+E3)*設定!$B$5*(1+設定!$B$6)+F3) | J3: =IF(D3="","",ROUND((D3+E3)*設定!$B$5,0)) | K3: =IF(D3="","",IF(J3<=設定!$B$9,0,ROUNDDOWN(J3*設定!$B$7,0))) | L3: =IF(D3="","",IF(J3<=設定!$B$9,0,ROUNDDOWN((J3+K3)*設定!$B$8,0))) | M3: =IF(D3="","",IF(J3<=設定!$B$9,0,設定!$B$10)) | N3: =IF(D3="","",I3+K3+L3+M3) | O3: =IF(G3="","",ROUNDDOWN(G3*設定!$B$11,0)) | P3: =IF(G3="","",設定!$B$12) | Q3: =IF(OR(D3="",G3=""),"",G3-O3-P3-N3) | R3: =IF(OR(Q3="",G3=0),"",Q3/G3) | S3: =IF(Q3="","",IF(AND(Q3>=設定!$B$13,R3>=設定!$B$14),"仕入れOK","見送り"))
I4: =IF(D4="","",(D4+E4)*設定!$B$5*(1+設定!$B$6)+F4) | J4: =IF(D4="","",ROUND((D4+E4)*設定!$B$5,0)) | K4: =IF(D4="","",IF(J4<=設定!$B$9,0,ROUNDDOWN(J4*設定!$B$7,0))) | L4: =IF(D4="","",IF(J4<=設定!$B$9,0,ROUNDDOWN((J4+K4)*設定!$B$8,0))) | M4: =IF(D4="","",IF(J4<=設定!$B$9,0,設定!$B$10)) | N4: =IF(D4="","",I4+K4+L4+M4) | O4: =IF(G4="","",ROUNDDOWN(G4*設定!$B$11,0)) | P4: =IF(G4="","",設定!$B$12) | Q4: =IF(OR(D4="",G4=""),"",G4-O4-P4-N4) | R4: =IF(OR(Q4="",G4=0),"",Q4/G4) | S4: =IF(Q4="","",IF(AND(Q4>=設定!$B$13,R4>=設定!$B$14),"仕入れOK","見送り"))
I5: =IF(D5="","",(D5+E5)*設定!$B$5*(1+設定!$B$6)+F5) | J5: =IF(D5="","",ROUND((D5+E5)*設定!$B$5,0)) | K5: =IF(D5="","",IF(J5<=設定!$B$9,0,ROUNDDOWN(J5*設定!$B$7,0))) | L5: =IF(D5="","",IF(J5<=設定!$B$9,0,ROUNDDOWN((J5+K5)*設定!$B$8,0))) | M5: =IF(D5="","",IF(J5<=設定!$B$9,0,設定!$B$10)) | N5: =IF(D5="","",I5+K5+L5+M5) | O5: =IF(G5="","",ROUNDDOWN(G5*設定!$B$11,0)) | P5: =IF(G5="","",設定!$B$12) | Q5: =IF(OR(D5="",G5=""),"",G5-O5-P5-N5) | R5: =IF(OR(Q5="",G5=0),"",Q5/G5) | S5: =IF(Q5="","",IF(AND(Q5>=設定!$B$13,R5>=設定!$B$14),"仕入れOK","見送り"))
I6: =IF(D6="","",(D6+E6)*設定!$B$5*(1+設定!$B$6)+F6) | J6: =IF(D6="","",ROUND((D6+E6)*設定!$B$5,0)) | K6: =IF(D6="","",IF(J6<=設定!$B$9,0,ROUNDDOWN(J6*設定!$B$7,0))) | L6: =IF(D6="","",IF(J6<=設定!$B$9,0,ROUNDDOWN((J6+K6)*設定!$B$8,0))) | M6: =IF(D6="","",IF(J6<=設定!$B$9,0,設定!$B$10)) | N6: =IF(D6="","",I6+K6+L6+M6) | O6: =IF(G6="","",ROUNDDOWN(G6*設定!$B$11,0)) | P6: =IF(G6="","",設定!$B$12) | Q6: =IF(OR(D6="",G6=""),"",G6-O6-P6-N6) | R6: =IF(OR(Q6="",G6=0),"",Q6/G6) | S6: =IF(Q6="","",IF(AND(Q6>=設定!$B$13,R6>=設定!$B$14),"仕入れOK","見送り"))
I7: =IF(D7="","",(D7+E7)*設定!$B$5*(1+設定!$B$6)+F7) | J7: =IF(D7="","",ROUND((D7+E7)*設定!$B$5,0)) | K7: =IF(D7="","",IF(J7<=設定!$B$9,0,ROUNDDOWN(J7*設定!$B$7,0))) | L7: =IF(D7="","",IF(J7<=設定!$B$9,0,ROUNDDOWN((J7+K7)*設定!$B$8,0))) | M7: =IF(D7="","",IF(J7<=設定!$B$9,0,設定!$B$10)) | N7: =IF(D7="","",I7+K7+L7+M7) | O7: =IF(G7="","",ROUNDDOWN(G7*設定!$B$11,0)) | P7: =IF(G7="","",設定!$B$12) | Q7: =IF(OR(D7="",G7=""),"",G7-O7-P7-N7) | R7: =IF(OR(Q7="",G7=0),"",Q7/G7) | S7: =IF(Q7="","",IF(AND(Q7>=設定!$B$13,R7>=設定!$B$14),"仕入れOK","見送り"))
I8: =IF(D8="","",(D8+E8)*設定!$B$5*(1+設定!$B$6)+F8) | J8: =IF(D8="","",ROUND((D8+E8)*設定!$B$5,0)) | K8: =IF(D8="","",IF(J8<=設定!$B$9,0,ROUNDDOWN(J8*設定!$B$7,0))) | L8: =IF(D8="","",IF(J8<=設定!$B$9,0,ROUNDDOWN((J8+K8)*設定!$B$8,0))) | M8: =IF(D8="","",IF(J8<=設定!$B$9,0,設定!$B$10)) | N8: =IF(D8="","",I8+K8+L8+M8) | O8: =IF(G8="","",ROUNDDOWN(G8*設定!$B$11,0)) | P8: =IF(G8="","",設定!$B$12) | Q8: =IF(OR(D8="",G8=""),"",G8-O8-P8-N8) | R8: =IF(OR(Q8="",G8=0),"",Q8/G8) | S8: =IF(Q8="","",IF(AND(Q8>=設定!$B$13,R8>=設定!$B$14),"仕入れOK","見送り"))
I9: =IF(D9="","",(D9+E9)*設定!$B$5*(1+設定!$B$6)+F9) | J9: =IF(D9="","",ROUND((D9+E9)*設定!$B$5,0)) | K9: =IF(D9="","",IF(J9<=設定!$B$9,0,ROUNDDOWN(J9*設定!$B$7,0))) | L9: =IF(D9="","",IF(J9<=設定!$B$9,0,ROUNDDOWN((J9+K9)*設定!$B$8,0))) | M9: =IF(D9="","",IF(J9<=設定!$B$9,0,設定!$B$10)) | N9: =IF(D9="","",I9+K9+L9+M9) | O9: =IF(G9="","",ROUNDDOWN(G9*設定!$B$11,0)) | P9: =IF(G9="","",設定!$B$12) | Q9: =IF(OR(D9="",G9=""),"",G9-O9-P9-N9) | R9: =IF(OR(Q9="",G9=0),"",Q9/G9) | S9: =IF(Q9="","",IF(AND(Q9>=設定!$B$13,R9>=設定!$B$14),"仕入れOK","見送り"))
I10: =IF(D10="","",(D10+E10)*設定!$B$5*(1+設定!$B$6)+F10) | J10: =IF(D10="","",ROUND((D10+E10)*設定!$B$5,0)) | K10: =IF(D10="","",IF(J10<=設定!$B$9,0,ROUNDDOWN(J10*設定!$B$7,0))) | L10: =IF(D10="","",IF(J10<=設定!$B$9,0,ROUNDDOWN((J10+K10)*設定!$B$8,0))) | M10: =IF(D10="","",IF(J10<=設定!$B$9,0,設定!$B$10)) | N10: =IF(D10="","",I10+K10+L10+M10) | O10: =IF(G10="","",ROUNDDOWN(G10*設定!$B$11,0)) | P10: =IF(G10="","",設定!$B$12) | Q10: =IF(OR(D10="",G10=""),"",G10-O10-P10-N10) | R10: =IF(OR(Q10="",G10=0),"",Q10/G10) | S10: =IF(Q10="","",IF(AND(Q10>=設定!$B$13,R10>=設定!$B$14),"仕入れOK","見送り"))
I11: =IF(D11="","",(D11+E11)*設定!$B$5*(1+設定!$B$6)+F11) | J11: =IF(D11="","",ROUND((D11+E11)*設定!$B$5,0)) | K11: =IF(D11="","",IF(J11<=設定!$B$9,0,ROUNDDOWN(J11*設定!$B$7,0))) | L11: =IF(D11="","",IF(J11<=設定!$B$9,0,ROUNDDOWN((J11+K11)*設定!$B$8,0))) | M11: =IF(D11="","",IF(J11<=設定!$B$9,0,設定!$B$10)) | N11: =IF(D11="","",I11+K11+L11+M11) | O11: =IF(G11="","",ROUNDDOWN(G11*設定!$B$11,0)) | P11: =IF(G11="","",設定!$B$12) | Q11: =IF(OR(D11="",G11=""),"",G11-O11-P11-N11) | R11: =IF(OR(Q11="",G11=0),"",Q11/G11) | S11: =IF(Q11="","",IF(AND(Q11>=設定!$B$13,R11>=設定!$B$14),"仕入れOK","見送り"))
I12: =IF(D12="","",(D12+E12)*設定!$B$5*(1+設定!$B$6)+F12) | J12: =IF(D12="","",ROUND((D12+E12)*設定!$B$5,0)) | K12: =IF(D12="","",IF(J12<=設定!$B$9,0,ROUNDDOWN(J12*設定!$B$7,0))) | L12: =IF(D12="","",IF(J12<=設定!$B$9,0,ROUNDDOWN((J12+K12)*設定!$B$8,0))) | M12: =IF(D12="","",IF(J12<=設定!$B$9,0,設定!$B$10)) | N12: =IF(D12="","",I12+K12+L12+M12) | O12: =IF(G12="","",ROUNDDOWN(G12*設定!$B$11,0)) | P12: =IF(G12="","",設定!$B$12) | Q12: =IF(OR(D12="",G12=""),"",G12-O12-P12-N12) | R12: =IF(OR(Q12="",G12=0),"",Q12/G12) | S12: =IF(Q12="","",IF(AND(Q12>=設定!$B$13,R12>=設定!$B$14),"仕入れOK","見送り"))
I13: =IF(D13="","",(D13+E13)*設定!$B$5*(1+設定!$B$6)+F13) | J13: =IF(D13="","",ROUND((D13+E13)*設定!$B$5,0)) | K13: =IF(D13="","",IF(J13<=設定!$B$9,0,ROUNDDOWN(J13*設定!$B$7,0))) | L13: =IF(D13="","",IF(J13<=設定!$B$9,0,ROUNDDOWN((J13+K13)*設定!$B$8,0))) | M13: =IF(D13="","",IF(J13<=設定!$B$9,0,設定!$B$10)) | N13: =IF(D13="","",I13+K13+L13+M13) | O13: =IF(G13="","",ROUNDDOWN(G13*設定!$B$11,0)) | P13: =IF(G13="","",設定!$B$12) | Q13: =IF(OR(D13="",G13=""),"",G13-O13-P13-N13) | R13: =IF(OR(Q13="",G13=0),"",Q13/G13) | S13: =IF(Q13="","",IF(AND(Q13>=設定!$B$13,R13>=設定!$B$14),"仕入れOK","見送り"))
I14: =IF(D14="","",(D14+E14)*設定!$B$5*(1+設定!$B$6)+F14) | J14: =IF(D14="","",ROUND((D14+E14)*設定!$B$5,0)) | K14: =IF(D14="","",IF(J14<=設定!$B$9,0,ROUNDDOWN(J14*設定!$B$7,0))) | L14: =IF(D14="","",IF(J14<=設定!$B$9,0,ROUNDDOWN((J14+K14)*設定!$B$8,0))) | M14: =IF(D14="","",IF(J14<=設定!$B$9,0,設定!$B$10)) | N14: =IF(D14="","",I14+K14+L14+M14) | O14: =IF(G14="","",ROUNDDOWN(G14*設定!$B$11,0)) | P14: =IF(G14="","",設定!$B$12) | Q14: =IF(OR(D14="",G14=""),"",G14-O14-P14-N14) | R14: =IF(OR(Q14="",G14=0),"",Q14/G14) | S14: =IF(Q14="","",IF(AND(Q14>=設定!$B$13,R14>=設定!$B$14),"仕入れOK","見送り"))
... I31: =IF(D31="","",(D31+E31)*設定!$B$5*(1+設定!$B$6)+F31) | J31: =IF(D31="","",ROUND((D31+E31)*設定!$B$5,0)) | K31: =IF(D31="","",IF(J31<=設定!$B$9,0,ROUNDDOWN(J31*設定!$B$7,0))) | L31: =IF(D31="","",IF(J31<=設定!$B$9,0,ROUNDDOWN((J31+K31)*設定!$B$8,0))) | M31: =IF(D31="","",IF(J31<=設定!$B$9,0,設定!$B$10)) | N31: =IF(D31="","",I31+K31+L31+M31) | O31: =IF(G31="","",ROUNDDOWN(G31*設定!$B$11,0)) | P31: =IF(G31="","",設定!$B$12) | Q31: =IF(OR(D31="",G31=""),"",G31-O31-P31-N31) | R31: =IF(OR(Q31="",G31=0),"",Q31/G31) | S31: =IF(Q31="","",IF(AND(Q31>=設定!$B$13,R31>=設定!$B$14),"仕入れOK","見送り"))
A33: 使い方: 黄色セルだけ入力。I〜S列は自動計算。2行目は記入例なので上書きしてOK。

Sheet 月次計画
A1: 月10万円 逆算シート
A2: 黄色セルを書き換えると、必要な件数・資金が自動で出ます。
A3: 項目 | B3: 値 | C3: メモ
A4: 月の目標利益（円） | B4: =設定!$B$15 -> 100000 | C4: 設定シートから連動
A5: 1件あたり平均利益（円） | B5: 6000 | C5: 仮の値。実績がたまったら取引記録の平均に置き換える
A6: 1件あたり平均仕入コスト（円） | B6: 30000 | C6: 仮の値。仕入れ判定シートの総仕入コスト平均が目安
A7: 仕入れ→入金までの日数 | B7: 30 | C7: 海外発送〜到着1〜3週間＋国内販売＋売上金入金までの目安
A8: 在庫が売れ残る割合（安全率） | B8: 0.2 | C8: 売れ残り・値下げに備えた資金の上乗せ
A9: 必要な販売件数（件/月） | B9: =ROUNDUP(B4/B5,0) -> 17 | C9: 目標利益 ÷ 1件利益
A10: 1日あたりの販売件数（件/日） | B10: =B9/30 -> 0.56666667
A11: 月の仕入総額（円） | B11: =B9*B6 -> 510000 | C11: 必要件数 × 1件仕入コスト
A12: 必要な運転資金の目安（円） | B12: =ROUNDUP(B11*MAX(B7,1)/30*(1+B8),-4) -> 620000 | C12: 月の仕入総額 × 回転日数/30 × (1+安全率)
A13: 月の売上目安（円） | B13: =B9*(B6+B5) -> 612000 | C13: 手数料・送料込みの概算
A16: 段階的な目標（小さく検証してから拡大）
A17: 期間 | B17: 目標利益(円) | C17: 販売件数の目安(件) | D17: やること
A18: 1ヶ月目 | B18: 10000 | C18: =IFERROR(ROUNDUP(B18/$B$5,0),"") -> 2 | D18: 相場リサーチ＋テスト仕入れ3〜5件。手数料・送料・到着日数の実数を把握
A19: 2ヶ月目 | B19: 30000 | C19: =IFERROR(ROUNDUP(B19/$B$5,0),"") -> 5 | D19: 利益が出たジャンル・価格帯に絞って件数を増やす
A20: 3ヶ月目 | B20: 60000 | C20: =IFERROR(ROUNDUP(B20/$B$5,0),"") -> 10 | D20: 仕入先セラーを固定化し、まとめ買いで送料を圧縮
A21: 4ヶ月目〜 | B21: 100000 | C21: =IFERROR(ROUNDUP(B21/$B$5,0),"") -> 17 | D21: 月10万円の安定化。取引記録をAIで分析して勝ちパターンを強化

Sheet 取引記録
A1: 仕入日 | B1: 販売日 | C1: カード名 | D1: 型番 | E1: 状態 | F1: 仕入先 | G1: 販売先 | H1: 総仕入コスト(円) | I1: 販売価格(円) | J1: 販売手数料(円) | K1: 国内送料(円) | L1: 利益(円) | M1: 利益率 | N1: 在庫日数 | O1: メモ（なぜ仕入れた/なぜ売れた） | Q1: 合計利益(円) | R1: =SUM(L2:L101) -> 6676
A2: 46266 | B2: 46285 | C2: （記入例）リザードン | D2: PSA10 | E2: 鑑定品 | F2: eBay | G2: メルカリ | H2: 36294 | I2: 48000 | J2: =IF(I2="","",ROUNDDOWN(I2*設定!$B$11,0)) -> 4800 | K2: =IF(I2="","",設定!$B$12) -> 230 | L2: =IF(OR(H2="",I2=""),"",I2-H2-J2-K2) -> 6676 | M2: =IF(OR(L2="",I2=0),"",L2/I2) -> 0.13908333 | N2: =IF(OR(A2="",B2=""),"",B2-A2) -> 19 | O2: 海外Soldより国内相場が高く、PSA証明番号で真贋確認済み | Q2: 取引件数 | R2: =COUNT(L2:L101) -> 1
J3: =IF(I3="","",ROUNDDOWN(I3*設定!$B$11,0)) | K3: =IF(I3="","",設定!$B$12) | L3: =IF(OR(H3="",I3=""),"",I3-H3-J3-K3) | M3: =IF(OR(L3="",I3=0),"",L3/I3) | N3: =IF(OR(A3="",B3=""),"",B3-A3) | Q3: 平均利益(円) | R3: =IFERROR(AVERAGE(L2:L101),0) -> 6676
J4: =IF(I4="","",ROUNDDOWN(I4*設定!$B$11,0)) | K4: =IF(I4="","",設定!$B$12) | L4: =IF(OR(H4="",I4=""),"",I4-H4-J4-K4) | M4: =IF(OR(L4="",I4=0),"",L4/I4) | N4: =IF(OR(A4="",B4=""),"",B4-A4) | Q4: 平均在庫日数 | R4: =IFERROR(AVERAGE(N2:N101),0) -> 19
J5: =IF(I5="","",ROUNDDOWN(I5*設定!$B$11,0)) | K5: =IF(I5="","",設定!$B$12) | L5: =IF(OR(H5="",I5=""),"",I5-H5-J5-K5) | M5: =IF(OR(L5="",I5=0),"",L5/I5) | N5: =IF(OR(A5="",B5=""),"",B5-A5)
J6: =IF(I6="","",ROUNDDOWN(I6*設定!$B$11,0)) | K6: =IF(I6="","",設定!$B$12) | L6: =IF(OR(H6="",I6=""),"",I6-H6-J6-K6) | M6: =IF(OR(L6="",I6=0),"",L6/I6) | N6: =IF(OR(A6="",B6=""),"",B6-A6)
J7: =IF(I7="","",ROUNDDOWN(I7*設定!$B$11,0)) | K7: =IF(I7="","",設定!$B$12) | L7: =IF(OR(H7="",I7=""),"",I7-H7-J7-K7) | M7: =IF(OR(L7="",I7=0),"",L7/I7) | N7: =IF(OR(A7="",B7=""),"",B7-A7)
J8: =IF(I8="","",ROUNDDOWN(I8*設定!$B$11,0)) | K8: =IF(I8="","",設定!$B$12) | L8: =IF(OR(H8="",I8=""),"",I8-H8-J8-K8) | M8: =IF(OR(L8="",I8=0),"",L8/I8) | N8: =IF(OR(A8="",B8=""),"",B8-A8)
J9: =IF(I9="","",ROUNDDOWN(I9*設定!$B$11,0)) | K9: =IF(I9="","",設定!$B$12) | L9: =IF(OR(H9="",I9=""),"",I9-H9-J9-K9) | M9: =IF(OR(L9="",I9=0),"",L9/I9) | N9: =IF(OR(A9="",B9=""),"",B9-A9)
J10: =IF(I10="","",ROUNDDOWN(I10*設定!$B$11,0)) | K10: =IF(I10="","",設定!$B$12) | L10: =IF(OR(H10="",I10=""),"",I10-H10-J10-K10) | M10: =IF(OR(L10="",I10=0),"",L10/I10) | N10: =IF(OR(A10="",B10=""),"",B10-A10)
J11: =IF(I11="","",ROUNDDOWN(I11*設定!$B$11,0)) | K11: =IF(I11="","",設定!$B$12) | L11: =IF(OR(H11="",I11=""),"",I11-H11-J11-K11) | M11: =IF(OR(L11="",I11=0),"",L11/I11) | N11: =IF(OR(A11="",B11=""),"",B11-A11)
J12: =IF(I12="","",ROUNDDOWN(I12*設定!$B$11,0)) | K12: =IF(I12="","",設定!$B$12) | L12: =IF(OR(H12="",I12=""),"",I12-H12-J12-K12) | M12: =IF(OR(L12="",I12=0),"",L12/I12) | N12: =IF(OR(A12="",B12=""),"",B12-A12)
J13: =IF(I13="","",ROUNDDOWN(I13*設定!$B$11,0)) | K13: =IF(I13="","",設定!$B$12) | L13: =IF(OR(H13="",I13=""),"",I13-H13-J13-K13) | M13: =IF(OR(L13="",I13=0),"",L13/I13) | N13: =IF(OR(A13="",B13=""),"",B13-A13)
J14: =IF(I14="","",ROUNDDOWN(I14*設定!$B$11,0)) | K14: =IF(I14="","",設定!$B$12) | L14: =IF(OR(H14="",I14=""),"",I14-H14-J14-K14) | M14: =IF(OR(L14="",I14=0),"",L14/I14) | N14: =IF(OR(A14="",B14=""),"",B14-A14)
J15: =IF(I15="","",ROUNDDOWN(I15*設定!$B$11,0)) | K15: =IF(I15="","",設定!$B$12) | L15: =IF(OR(H15="",I15=""),"",I15-H15-J15-K15) | M15: =IF(OR(L15="",I15=0),"",L15/I15) | N15: =IF(OR(A15="",B15=""),"",B15-A15)
J16: =IF(I16="","",ROUNDDOWN(I16*設定!$B$11,0)) | K16: =IF(I16="","",設定!$B$12) | L16: =IF(OR(H16="",I16=""),"",I16-H16-J16-K16) | M16: =IF(OR(L16="",I16=0),"",L16/I16) | N16: =IF(OR(A16="",B16=""),"",B16-A16)
... J101: =IF(I101="","",ROUNDDOWN(I101*設定!$B$11,0)) | K101: =IF(I101="","",設定!$B$12) | L101: =IF(OR(H101="",I101=""),"",I101-H101-J101-K101) | M101: =IF(OR(L101="",I101=0),"",L101/I101) | N101: =IF(OR(A101="",B101=""),"",B101-A101)
